monary_mongo/__init__.py
monary_mongo/cmonary.c
monary_mongo/datehelper.py
monary_mongo/main.py
monary_mongo/monary_mongo.py
monary_mongo/monary_param.py
monary_mongo/ordereddict.py
monary_mongo/write_concern.py
monary_mongo/libcmonary.cpython-311-x86_64-linux-gnu.so
monary_mongo-0.6.2.dist-info/LICENSE.TXT
monary_mongo-0.6.2.dist-info/METADATA
monary_mongo-0.6.2.dist-info/WHEEL
monary_mongo-0.6.2.dist-info/RECORD
